fastapiMpesa/__init__.py
fastapiMpesa/api/__init__.py
fastapiMpesa/api/auth.py
fastapiMpesa/api/b2b.py
fastapiMpesa/api/b2c.py
fastapiMpesa/api/balance.py
fastapiMpesa/api/c2b.py
fastapiMpesa/api/mpesa_express.py
fastapiMpesa/api/reversal.py
fastapiMpesa/api/transaction_status.py
fastapiMpesa/tests/__init__.py
fastapiMpesa/tests/base.py
fastapiMpesa/tests/conftest.py
fastapiMpesa/tests/data.py
fastapiMpesa/tests/test_base.py
fastapiMpesa-0.0.1.dist-info/LICENSE
fastapiMpesa-0.0.1.dist-info/METADATA
fastapiMpesa-0.0.1.dist-info/WHEEL
fastapiMpesa-0.0.1.dist-info/top_level.txt
fastapiMpesa-0.0.1.dist-info/RECORD
